django_query_tracer-0.2.2.dist-info/DESCRIPTION.rst
django_query_tracer-0.2.2.dist-info/METADATA
django_query_tracer-0.2.2.dist-info/RECORD
django_query_tracer-0.2.2.dist-info/WHEEL
django_query_tracer-0.2.2.dist-info/metadata.json
django_query_tracer-0.2.2.dist-info/top_level.txt
query_tracer/__init__.py
query_tracer/admin.py
query_tracer/apps.py
query_tracer/logger.py
query_tracer/middleware.py
query_tracer/models.py
query_tracer/settings.py
query_tracer/tests.py
query_tracer/views.py
query_tracer/migrations/__init__.py
query_tracer/modules/__init__.py
query_tracer/modules/ajax.py
query_tracer/modules/sql.py
query_tracer/modules/time.py
query_tracer/utils/__init__.py
query_tracer/utils/time.py
query_tracer/utils/trace.py
