Metadata-Version: 2.0
Name: django-query-tracer
Version: 0.2.2
Summary: A simplified version of django-devserver limited to SQL tracing and Ajax dump.
Home-page: https://github.com/morlandi/django-query-tracer
Author: Mario Orlandi
Author-email: morlandi@brainstorm.it
License: MIT
Keywords: django-query-tracer
Platform: UNKNOWN
Classifier: Development Status :: 3 - Alpha
Classifier: Framework :: Django
Classifier: Framework :: Django :: 1.8
Classifier: Framework :: Django :: 1.9
Classifier: Framework :: Django :: 1.10
Classifier: Intended Audience :: Developers
Classifier: License :: OSI Approved :: BSD License
Classifier: Natural Language :: English
Classifier: Programming Language :: Python :: 2
Classifier: Programming Language :: Python :: 2.7
Classifier: Programming Language :: Python :: 3
Classifier: Programming Language :: Python :: 3.3
Classifier: Programming Language :: Python :: 3.4
Classifier: Programming Language :: Python :: 3.5
